COPYING.LESSER
COPYING.gpl3
LICENSES
MANIFEST.in
README.rst
setup.py
aioxmpp/__init__.py
aioxmpp/_version.py
aioxmpp/cache.py
aioxmpp/callbacks.py
aioxmpp/connector.py
aioxmpp/custom_queue.py
aioxmpp/dispatcher.py
aioxmpp/errors.py
aioxmpp/hashes.py
aioxmpp/i18n.py
aioxmpp/network.py
aioxmpp/node.py
aioxmpp/nonza.py
aioxmpp/protocol.py
aioxmpp/rfc3921.py
aioxmpp/rfc6120.py
aioxmpp/sasl.py
aioxmpp/security_layer.py
aioxmpp/service.py
aioxmpp/ssl_transport.py
aioxmpp/stanza.py
aioxmpp/statemachine.py
aioxmpp/stream.py
aioxmpp/stringprep.py
aioxmpp/structs.py
aioxmpp/tasks.py
aioxmpp/testutils.py
aioxmpp/tracking.py
aioxmpp/utils.py
aioxmpp/xml.py
aioxmpp/xmltestutils.py
aioxmpp.egg-info/PKG-INFO
aioxmpp.egg-info/SOURCES.txt
aioxmpp.egg-info/dependency_links.txt
aioxmpp.egg-info/requires.txt
aioxmpp.egg-info/top_level.txt
aioxmpp/adhoc/__init__.py
aioxmpp/adhoc/service.py
aioxmpp/adhoc/xso.py
aioxmpp/avatar/__init__.py
aioxmpp/avatar/service.py
aioxmpp/avatar/xso.py
aioxmpp/benchtest/__init__.py
aioxmpp/benchtest/__main__.py
aioxmpp/blocking/__init__.py
aioxmpp/blocking/service.py
aioxmpp/blocking/xso.py
aioxmpp/bookmarks/__init__.py
aioxmpp/bookmarks/service.py
aioxmpp/bookmarks/xso.py
aioxmpp/carbons/__init__.py
aioxmpp/carbons/service.py
aioxmpp/carbons/xso.py
aioxmpp/chatstates/__init__.py
aioxmpp/chatstates/utils.py
aioxmpp/chatstates/xso.py
aioxmpp/disco/__init__.py
aioxmpp/disco/service.py
aioxmpp/disco/xso.py
aioxmpp/e2etest/__init__.py
aioxmpp/e2etest/__main__.py
aioxmpp/e2etest/provision.py
aioxmpp/e2etest/utils.py
aioxmpp/entitycaps/__init__.py
aioxmpp/entitycaps/caps115.py
aioxmpp/entitycaps/caps390.py
aioxmpp/entitycaps/common.py
aioxmpp/entitycaps/service.py
aioxmpp/entitycaps/xso.py
aioxmpp/extservice/__init__.py
aioxmpp/extservice/xso.py
aioxmpp/forms/__init__.py
aioxmpp/forms/fields.py
aioxmpp/forms/form.py
aioxmpp/forms/xso.py
aioxmpp/httpupload/__init__.py
aioxmpp/httpupload/xso.py
aioxmpp/ibb/__init__.py
aioxmpp/ibb/service.py
aioxmpp/ibb/xso.py
aioxmpp/ibr/__init__.py
aioxmpp/ibr/service.py
aioxmpp/ibr/xso.py
aioxmpp/im/__init__.py
aioxmpp/im/body.py
aioxmpp/im/conversation.py
