Metadata-Version: 2.1
Name: aioxmpp
Version: 0.13.1
Summary: Pure-python XMPP library for asyncio
Home-page: https://github.com/horazont/aioxmpp
Author: Jonas Schäfer
Author-email: jonas@wielicki.name
License: LGPLv3+
Keywords: asyncio xmpp library
Platform: UNKNOWN
Classifier: Development Status :: 4 - Beta
Classifier: Intended Audience :: Developers
Classifier: Operating System :: POSIX
Classifier: License :: OSI Approved :: GNU Lesser General Public License v3 or later (LGPLv3+)
Classifier: Programming Language :: Python :: 3 :: Only
Classifier: Programming Language :: Python :: 3.5
Classifier: Programming Language :: Python :: 3.6
Classifier: Programming Language :: Python :: 3.7
Classifier: Programming Language :: Python :: 3.8
Classifier: Programming Language :: Python :: 3.9
Classifier: Topic :: Communications :: Chat
Classifier: Topic :: Internet :: XMPP
License-File: LICENSES
License-File: COPYING.LESSER
License-File: COPYING.gpl3
